__init__.py
omicsone_data/__init__.py
omicsone_data/main.py
omicsone_data/plugins/data.cp39-win_amd64.pyd
omicsone_data/plugins/param.cp39-win_amd64.pyd
omicsone_data-0.1.3.dist-info/LICENSE
omicsone_data-0.1.3.dist-info/METADATA
omicsone_data-0.1.3.dist-info/WHEEL
omicsone_data-0.1.3.dist-info/entry_points.txt
omicsone_data-0.1.3.dist-info/top_level.txt
omicsone_data-0.1.3.dist-info/RECORD
